ilonnx/__init__.py
ilonnx/lib.py
ilonnx/py.typed
ilonnx/factory/__init__.py
ilonnx/factory/base.py
ilonnx/inference/__init__.py
ilonnx/inference/base.py
ilonnx/inference/classifier.py
ilonnx/inference/encoder.py
ilonnx/inference/factory.py
ilonnx/inference/parsing.py
ilonnx/inference/translators.py
ilonnx/inference/utils.py
tests/__init__.py
instancelib_onnx-0.1.3.dist-info/LICENSE
instancelib_onnx-0.1.3.dist-info/METADATA
instancelib_onnx-0.1.3.dist-info/WHEEL
instancelib_onnx-0.1.3.dist-info/top_level.txt
instancelib_onnx-0.1.3.dist-info/RECORD
